easy_server_indexing/__init__.py
easy_server_indexing/__main.py__.py
easy_server_indexing/resume.py
easy_server_indexing-0.1.1.dist-info/LICENSE
easy_server_indexing-0.1.1.dist-info/METADATA
easy_server_indexing-0.1.1.dist-info/WHEEL
easy_server_indexing-0.1.1.dist-info/top_level.txt
easy_server_indexing-0.1.1.dist-info/RECORD
